e3dump/__init__.py
e3dump/__main__.py
e3dump/auth.py
e3dump/cli.py
e3dump/fetcher.py
e3dump/main.py
e3dump/utils.py
e3dump-1.0.0.dist-info/entry_points.txt
e3dump-1.0.0.dist-info/LICENSE
e3dump-1.0.0.dist-info/WHEEL
e3dump-1.0.0.dist-info/METADATA
e3dump-1.0.0.dist-info/RECORD
