Metadata-Version: 2.1
Name: e3dump
Version: 1.0.0
Summary: e3dump - dump your NCTU e3 course materials by one click
Home-page: https://github.com/mlouielu/e3dump
License: UNKNOWN
Author: Louie Lu
Author-email: git@louie.lu
Requires-Python: >=3.6
Classifier: License :: OSI Approved :: MIT License
Requires-Dist: aiohttp
Requires-Dist: aiodns
Requires-Dist: cchardet
Requires-Dist: lxml
Requires-Dist: colorlog
Provides-Extra: .none
